ConsulJianjieHeKuaisuRumen/README.md
ConsulJianjieHeKuaisuRumen/__init__.py
ConsulJianjieHeKuaisuRumen/__main__.py
ConsulJianjieHeKuaisuRumen/file.epub
ConsulJianjieHeKuaisuRumen/index.html
ConsulJianjieHeKuaisuRumen/css/__init__.py
ConsulJianjieHeKuaisuRumen/css/annotations.css
ConsulJianjieHeKuaisuRumen/css/main.css
ConsulJianjieHeKuaisuRumen/css/normalize.css
ConsulJianjieHeKuaisuRumen/css/popup.css
ConsulJianjieHeKuaisuRumen/font/__init__.py
ConsulJianjieHeKuaisuRumen/font/fontello.eot
ConsulJianjieHeKuaisuRumen/font/fontello.svg
ConsulJianjieHeKuaisuRumen/font/fontello.ttf
ConsulJianjieHeKuaisuRumen/font/fontello.woff
ConsulJianjieHeKuaisuRumen/img/__init__.py
ConsulJianjieHeKuaisuRumen/img/annotator-glyph-sprite.png
ConsulJianjieHeKuaisuRumen/img/annotator-icon-sprite.png
ConsulJianjieHeKuaisuRumen/img/apple-touch-icon.png
ConsulJianjieHeKuaisuRumen/img/cancelfullscreen.png
ConsulJianjieHeKuaisuRumen/img/close.png
ConsulJianjieHeKuaisuRumen/img/fullscreen.png
ConsulJianjieHeKuaisuRumen/img/loader.gif
ConsulJianjieHeKuaisuRumen/img/menu-icon.png
ConsulJianjieHeKuaisuRumen/img/save.png
ConsulJianjieHeKuaisuRumen/img/saved.png
ConsulJianjieHeKuaisuRumen/img/settings-s.png
ConsulJianjieHeKuaisuRumen/img/settings.png
ConsulJianjieHeKuaisuRumen/img/star.png
ConsulJianjieHeKuaisuRumen/js/__init__.py
ConsulJianjieHeKuaisuRumen/js/epub.js
ConsulJianjieHeKuaisuRumen/js/epub.min.js
ConsulJianjieHeKuaisuRumen/js/epub.min.map
ConsulJianjieHeKuaisuRumen/js/hooks.min.js
ConsulJianjieHeKuaisuRumen/js/hooks.min.map
ConsulJianjieHeKuaisuRumen/js/reader.js
ConsulJianjieHeKuaisuRumen/js/reader.js.map
ConsulJianjieHeKuaisuRumen/js/reader.min.js
ConsulJianjieHeKuaisuRumen/js/reader.min.map
ConsulJianjieHeKuaisuRumen/js/hooks/__init__.py
ConsulJianjieHeKuaisuRumen/js/hooks/extensions/__init__.py
ConsulJianjieHeKuaisuRumen/js/hooks/extensions/highlight.js
ConsulJianjieHeKuaisuRumen/js/libs/__init__.py
ConsulJianjieHeKuaisuRumen/js/libs/jquery.min.js
consul_jianjie_he_kuaisu_rumen-2024.3.3.0.dist-info/METADATA
consul_jianjie_he_kuaisu_rumen-2024.3.3.0.dist-info/WHEEL
consul_jianjie_he_kuaisu_rumen-2024.3.3.0.dist-info/entry_points.txt
consul_jianjie_he_kuaisu_rumen-2024.3.3.0.dist-info/top_level.txt
consul_jianjie_he_kuaisu_rumen-2024.3.3.0.dist-info/RECORD
